iupy_device42api/__init__.py
iupy_device42api/device42api.py
iupy_device42api-0.1.2.dist-info/LICENSE
iupy_device42api-0.1.2.dist-info/METADATA
iupy_device42api-0.1.2.dist-info/WHEEL
iupy_device42api-0.1.2.dist-info/top_level.txt
iupy_device42api-0.1.2.dist-info/RECORD
