Metadata-Version: 2.2
Name: iupy-device42api
Version: 0.1.2
Summary: Ian Underwood's Device42 API
Author-email: "Ian A. Underwood" <ian@underwood-hq.org>
License: MIT
Project-URL: Repository, https://github.com/iunderwood/iupy-device42api
Keywords: Device42
Classifier: Development Status :: 3 - Alpha
Classifier: Intended Audience :: Developers
Classifier: Natural Language :: English
Classifier: Operating System :: OS Independent
Classifier: Programming Language :: Python
Classifier: Topic :: Utilities
License-File: LICENSE
Requires-Dist: requests~=2.32.4
Requires-Dist: urllib3~=2.5.0
